MANIFEST.in
etcd3ctl.py
setup.py
ha_etcd3.egg-info/PKG-INFO
ha_etcd3.egg-info/SOURCES.txt
ha_etcd3.egg-info/dependency_links.txt
ha_etcd3.egg-info/not-zip-safe
ha_etcd3.egg-info/requires.txt
ha_etcd3.egg-info/top_level.txt