Metadata-Version: 1.1
Name: ha-etcd3
Version: 1.0.2
Summary: high-available lib for single point of failure
Home-page: https://pypi.python.org/pypi/ha-etcd3
Author: Lafite93
Author-email: 227337844@qq.com
License: MIT
Keywords: ha failover single
Platform: UNKNOWN
Classifier: License :: OSI Approved :: MIT License
Classifier: Development Status :: 3 - Alpha
Classifier: Programming Language :: Python :: 3
Classifier: Programming Language :: Python :: 3.5
